odoo/addons/test_queue_job_batch/README.rst
odoo/addons/test_queue_job_batch/__init__.py
odoo/addons/test_queue_job_batch/__manifest__.py
odoo/addons/test_queue_job_batch/i18n/fr.po
odoo/addons/test_queue_job_batch/i18n/test_queue_job_batch.pot
odoo/addons/test_queue_job_batch/readme/CONTRIBUTORS.rst
odoo/addons/test_queue_job_batch/readme/DESCRIPTION.rst
odoo/addons/test_queue_job_batch/static/description/icon.png
odoo/addons/test_queue_job_batch/static/description/icon.svg
odoo/addons/test_queue_job_batch/static/description/index.html
odoo/addons/test_queue_job_batch/tests/__init__.py
odoo/addons/test_queue_job_batch/tests/test_queue_job_batch.py
odoo12_addon_test_queue_job_batch-12.0.1.1.0.99.dev6.dist-info/METADATA
odoo12_addon_test_queue_job_batch-12.0.1.1.0.99.dev6.dist-info/WHEEL
odoo12_addon_test_queue_job_batch-12.0.1.1.0.99.dev6.dist-info/top_level.txt
odoo12_addon_test_queue_job_batch-12.0.1.1.0.99.dev6.dist-info/RECORD
