Metadata-Version: 2.1
Name: odoo12-addon-test-queue-job-batch
Version: 12.0.1.1.0.99.dev6
Summary: Test Job Queue Batch
Home-page: https://github.com/OCA/queue
Author: Creu Blanca,Odoo Community Association (OCA)
Author-email: support@odoo-community.org
License: AGPL-3
Platform: UNKNOWN
Classifier: Programming Language :: Python
Classifier: Framework :: Odoo
Classifier: Framework :: Odoo :: 12.0
Classifier: License :: OSI Approved :: GNU Affero General Public License v3
Requires-Python: >=3.5
Requires-Dist: odoo12-addon-queue-job-batch
Requires-Dist: odoo12-addon-test-queue-job
Requires-Dist: odoo <12.1dev,>=12.0a
